riddlesolver/__init__.py
riddlesolver/app.py
riddlesolver/config.py
riddlesolver/constants.py
riddlesolver/repository.py
riddlesolver/requirements.txt
riddlesolver/setup.py
riddlesolver/streamlit_app.py
riddlesolver/summary.py
riddlesolver/utils.py
riddlesolver-0.1.20.dist-info/METADATA
riddlesolver-0.1.20.dist-info/WHEEL
riddlesolver-0.1.20.dist-info/entry_points.txt
riddlesolver-0.1.20.dist-info/licenses/LICENSE
riddlesolver-0.1.20.dist-info/RECORD
