Metadata-Version: 2.3
Name: riddlesolver
Version: 0.1.20
Summary: A command-line tool to summarize Git commits using OpenAI ChatGPT
Author-email: Siyuan Wu <cushmily@gmail.com>
License-Expression: MIT
License-File: LICENSE
Classifier: Development Status :: 3 - Alpha
Classifier: Intended Audience :: Developers
Classifier: License :: OSI Approved :: MIT License
Classifier: Programming Language :: Python :: 3
Classifier: Programming Language :: Python :: 3 :: Only
Classifier: Programming Language :: Python :: 3.8
Classifier: Programming Language :: Python :: 3.9
Classifier: Programming Language :: Python :: 3.10
Classifier: Programming Language :: Python :: 3.11
Requires-Python: >=3.8
Requires-Dist: configparser
Requires-Dist: gitpython
Requires-Dist: openai
Requires-Dist: pyperclip
Requires-Dist: python-dateutil
Requires-Dist: requests
